{
    "FileVersion": "2025.9.30",
    "EnableAddressable": false,
    "SupportExtensionless": true,
    "LocationToLower": false,
    "IncludeAssetGUID": false,
    "ReplaceAssetPathWithAddress": false,
    "OutputNameStyle": 0,
    "BuildBundleType": 1,
    "BuildPipeline": "EditorSimulateBuildPipeline",
    "PackageName": "DefaultPackage",
    "PackageVersion": "Simulate",
    "PackageNote": "2026/2/9 17:20:28",
    "AssetList": [
        {
            "Address": "",
            "AssetPath": "Assets/AAAGame/DataTable/CameraViewTable.bytes",
            "AssetGUID": "",
            "AssetTags": [],
            "BundleID": 0,
            "DependBundleIDs": []
        },
        {
            "Address": "",
            "AssetPath": "Assets/AAAGame/DataTable/CameraViewTable.txt",
            "AssetGUID": "",
            "AssetTags": [],
            "BundleID": 0,
            "DependBundleIDs": []
        },
        {
            "Address": "",
            "AssetPath": "Assets/AAAGame/DataTable/ColorTable.bytes",
            "AssetGUID": "",
            "AssetTags": [],
            "BundleID": 0,
            "DependBundleIDs": []
        },
        {
            "Address": "",
            "AssetPath": "Assets/AAAGame/DataTable/ColorTable.txt",
            "AssetGUID": "",
            "AssetTags": [],
            "BundleID": 0,
            "DependBundleIDs": []
        },
        {
            "Address": "",
            "AssetPath": "Assets/AAAGame/DataTable/CombatUnitTable.bytes",
            "AssetGUID": "",
            "AssetTags": [],
            "BundleID": 0,
            "DependBundleIDs": []
        },
        {
            "Address": "",
            "AssetPath": "Assets/AAAGame/DataTable/CombatUnitTable.txt",
            "AssetGUID": "",
            "AssetTags": [],
            "BundleID": 0,
            "DependBundleIDs": []
        },
        {
            "Address": "",
            "AssetPath": "Assets/AAAGame/DataTable/Core/EntityGroupTable.bytes",
            "AssetGUID": "",
            "AssetTags": [],
            "BundleID": 1,
            "DependBundleIDs": []
        },
        {
            "Address": "",
            "AssetPath": "Assets/AAAGame/DataTable/Core/EntityGroupTable.txt",
            "AssetGUID": "",
            "AssetTags": [],
            "BundleID": 1,
            "DependBundleIDs": []
        },
        {
            "Address": "",
            "AssetPath": "Assets/AAAGame/DataTable/Core/LanguagesTable.bytes",
            "AssetGUID": "",
            "AssetTags": [],
            "BundleID": 1,
            "DependBundleIDs": []
        },
        {
            "Address": "",
            "AssetPath": "Assets/AAAGame/DataTable/Core/LanguagesTable.txt",
            "AssetGUID": "",
            "AssetTags": [],
            "BundleID": 1,
            "DependBundleIDs": []
        },
        {
            "Address": "",
            "AssetPath": "Assets/AAAGame/DataTable/Core/SoundGroupTable.bytes",
            "AssetGUID": "",
            "AssetTags": [],
            "BundleID": 1,
            "DependBundleIDs": []
        },
        {
            "Address": "",
            "AssetPath": "Assets/AAAGame/DataTable/Core/SoundGroupTable.txt",
            "AssetGUID": "",
            "AssetTags": [],
            "BundleID": 1,
            "DependBundleIDs": []
        },
        {
            "Address": "",
            "AssetPath": "Assets/AAAGame/DataTable/Core/UIGroupTable.bytes",
            "AssetGUID": "",
            "AssetTags": [],
            "BundleID": 1,
            "DependBundleIDs": []
        },
        {
            "Address": "",
            "AssetPath": "Assets/AAAGame/DataTable/Core/UIGroupTable.txt",
            "AssetGUID": "",
            "AssetTags": [],
            "BundleID": 1,
            "DependBundleIDs": []
        },
        {
            "Address": "",
            "AssetPath": "Assets/AAAGame/DataTable/Core/UITable.bytes",
            "AssetGUID": "",
            "AssetTags": [],
            "BundleID": 1,
            "DependBundleIDs": []
        },
        {
            "Address": "",
            "AssetPath": "Assets/AAAGame/DataTable/Core/UITable.txt",
            "AssetGUID": "",
            "AssetTags": [],
            "BundleID": 1,
            "DependBundleIDs": []
        },
        {
            "Address": "",
            "AssetPath": "Assets/AAAGame/DataTable/LevelTable.bytes",
            "AssetGUID": "",
            "AssetTags": [],
            "BundleID": 0,
            "DependBundleIDs": []
        },
        {
            "Address": "",
            "AssetPath": "Assets/AAAGame/DataTable/LevelTable.txt",
            "AssetGUID": "",
            "AssetTags": [],
            "BundleID": 0,
            "DependBundleIDs": []
        },
        {
            "Address": "",
            "AssetPath": "Assets/AAAGame/DataTable/TestTable.bytes",
            "AssetGUID": "",
            "AssetTags": [],
            "BundleID": 0,
            "DependBundleIDs": []
        },
        {
            "Address": "",
            "AssetPath": "Assets/AAAGame/DataTable/TestTable.txt",
            "AssetGUID": "",
            "AssetTags": [],
            "BundleID": 0,
            "DependBundleIDs": []
        },
        {
            "Address": "",
            "AssetPath": "Assets/AAAGame/Scene/Launch.unity",
            "AssetGUID": "",
            "AssetTags": [],
            "BundleID": 2,
            "DependBundleIDs": []
        },
        {
            "Address": "",
            "AssetPath": "Assets/AAAGame/Scripts/Hotfix.asmdef",
            "AssetGUID": "",
            "AssetTags": [],
            "BundleID": 3,
            "DependBundleIDs": []
        },
        {
            "Address": "",
            "AssetPath": "Assets/AAAGame/ScriptsBuiltin/Runtime/Builtin.Runtime.asmdef",
            "AssetGUID": "",
            "AssetTags": [],
            "BundleID": 4,
            "DependBundleIDs": []
        },
        {
            "Address": "",
            "AssetPath": "Assets/Bundles/Animation/AnimCtrl.controller",
            "AssetGUID": "",
            "AssetTags": [],
            "BundleID": 5,
            "DependBundleIDs": []
        },
        {
            "Address": "",
            "AssetPath": "Assets/Bundles/Animation/HandMask.mask",
            "AssetGUID": "",
            "AssetTags": [],
            "BundleID": 5,
            "DependBundleIDs": []
        },
        {
            "Address": "",
            "AssetPath": "Assets/Bundles/Animation/Humanoid@death.fbx",
            "AssetGUID": "",
            "AssetTags": [],
            "BundleID": 5,
            "DependBundleIDs": []
        },
        {
            "Address": "",
            "AssetPath": "Assets/Bundles/Animation/Humanoid@IdleHold2Guns.FBX",
            "AssetGUID": "",
            "AssetTags": [],
            "BundleID": 5,
            "DependBundleIDs": []
        },
        {
            "Address": "",
            "AssetPath": "Assets/Bundles/Animation/Humanoid@RunForward2Guns.FBX",
            "AssetGUID": "",
            "AssetTags": [],
            "BundleID": 5,
            "DependBundleIDs": []
        },
        {
            "Address": "",
            "AssetPath": "Assets/Bundles/Animation/Humanoid@WalkForward2Guns.FBX",
            "AssetGUID": "",
            "AssetTags": [],
            "BundleID": 5,
            "DependBundleIDs": []
        },
        {
            "Address": "",
            "AssetPath": "Assets/Bundles/Animation/PlayerColorAnim.anim",
            "AssetGUID": "",
            "AssetTags": [],
            "BundleID": 5,
            "DependBundleIDs": []
        },
        {
            "Address": "",
            "AssetPath": "Assets/Bundles/Animation/PlayerCtrl.controller",
            "AssetGUID": "",
            "AssetTags": [],
            "BundleID": 5,
            "DependBundleIDs": []
        },
        {
            "Address": "",
            "AssetPath": "Assets/Bundles/Animation/UI/ToastTips_Close.anim",
            "AssetGUID": "",
            "AssetTags": [],
            "BundleID": 6,
            "DependBundleIDs": []
        },
        {
            "Address": "",
            "AssetPath": "Assets/Bundles/Animation/UI/ToastTips_Open.anim",
            "AssetGUID": "",
            "AssetTags": [],
            "BundleID": 6,
            "DependBundleIDs": []
        },
        {
            "Address": "",
            "AssetPath": "Assets/Bundles/Animation/UI/WaitingRotateAnim.anim",
            "AssetGUID": "",
            "AssetTags": [],
            "BundleID": 6,
            "DependBundleIDs": []
        },
        {
            "Address": "",
            "AssetPath": "Assets/Bundles/Audio/DefaultAudioMixer.mixer",
            "AssetGUID": "",
            "AssetTags": [],
            "BundleID": 7,
            "DependBundleIDs": []
        },
        {
            "Address": "",
            "AssetPath": "Assets/Bundles/Code/Unity.HotFix.dll.bytes",
            "AssetGUID": "",
            "AssetTags": [],
            "BundleID": 8,
            "DependBundleIDs": []
        },
        {
            "Address": "",
            "AssetPath": "Assets/Bundles/Config/GameConfig.bytes",
            "AssetGUID": "",
            "AssetTags": [],
            "BundleID": 9,
            "DependBundleIDs": []
        },
        {
            "Address": "",
            "AssetPath": "Assets/Bundles/Config/GameConfig.txt",
            "AssetGUID": "",
            "AssetTags": [],
            "BundleID": 9,
            "DependBundleIDs": []
        },
        {
            "Address": "",
            "AssetPath": "Assets/Bundles/Config/local_tblocalization.json",
            "AssetGUID": "",
            "AssetTags": [],
            "BundleID": 9,
            "DependBundleIDs": []
        },
        {
            "Address": "",
            "AssetPath": "Assets/Bundles/Config/tables_core_tbentitygrouptable.json",
            "AssetGUID": "",
            "AssetTags": [],
            "BundleID": 9,
            "DependBundleIDs": []
        },
        {
            "Address": "",
            "AssetPath": "Assets/Bundles/Config/tables_core_tblanguagestable.json",
            "AssetGUID": "",
            "AssetTags": [],
            "BundleID": 9,
            "DependBundleIDs": []
        },
        {
            "Address": "",
            "AssetPath": "Assets/Bundles/Config/tables_core_tbsoundgrouptable.json",
            "AssetGUID": "",
            "AssetTags": [],
            "BundleID": 9,
            "DependBundleIDs": []
        },
        {
            "Address": "",
            "AssetPath": "Assets/Bundles/Config/tables_core_tbuigrouptable.json",
            "AssetGUID": "",
            "AssetTags": [],
            "BundleID": 9,
            "DependBundleIDs": []
        },
        {
            "Address": "",
            "AssetPath": "Assets/Bundles/Config/tables_core_tbuitable.json",
            "AssetGUID": "",
            "AssetTags": [],
            "BundleID": 9,
            "DependBundleIDs": []
        },
        {
            "Address": "",
            "AssetPath": "Assets/Bundles/Config/tables_tbachievementconfig.json",
            "AssetGUID": "",
            "AssetTags": [],
            "BundleID": 9,
            "DependBundleIDs": []
        },
        {
            "Address": "",
            "AssetPath": "Assets/Bundles/Config/tables_tbcameraviewtable.json",
            "AssetGUID": "",
            "AssetTags": [],
            "BundleID": 9,
            "DependBundleIDs": []
        },
        {
            "Address": "",
            "AssetPath": "Assets/Bundles/Config/tables_tbcolortable.json",
            "AssetGUID": "",
            "AssetTags": [],
            "BundleID": 9,
            "DependBundleIDs": []
        },
        {
            "Address": "",
            "AssetPath": "Assets/Bundles/Config/tables_tbcombatunittable.json",
            "AssetGUID": "",
            "AssetTags": [],
            "BundleID": 9,
            "DependBundleIDs": []
        },
        {
            "Address": "",
            "AssetPath": "Assets/Bundles/Config/tables_tbitemconfig.json",
            "AssetGUID": "",
            "AssetTags": [],
            "BundleID": 9,
            "DependBundleIDs": []
        },
        {
            "Address": "",
            "AssetPath": "Assets/Bundles/Config/tables_tbleveltable.json",
            "AssetGUID": "",
            "AssetTags": [],
            "BundleID": 9,
            "DependBundleIDs": []
        },
        {
            "Address": "",
            "AssetPath": "Assets/Bundles/Config/tables_tbsoundsconfig.json",
            "AssetGUID": "",
            "AssetTags": [],
            "BundleID": 9,
            "DependBundleIDs": []
        },
        {
            "Address": "",
            "AssetPath": "Assets/Bundles/Font/Common/AlibabaPuHuiTi-3-85-Bold SDF.asset",
            "AssetGUID": "",
            "AssetTags": [],
            "BundleID": 10,
            "DependBundleIDs": []
        },
        {
            "Address": "",
            "AssetPath": "Assets/Bundles/Font/Common/AlibabaPuHuiTi-3-85-Bold.ttf",
            "AssetGUID": "",
            "AssetTags": [],
            "BundleID": 10,
            "DependBundleIDs": []
        },
        {
            "Address": "",
            "AssetPath": "Assets/Bundles/Font/Common/AlibabaPuHuiTi-3-85-Bold-Title SDF.mat",
            "AssetGUID": "",
            "AssetTags": [],
            "BundleID": 10,
            "DependBundleIDs": []
        },
        {
            "Address": "",
            "AssetPath": "Assets/Bundles/Font/Common/AlibabaSansJP SDF.asset",
            "AssetGUID": "",
            "AssetTags": [],
            "BundleID": 10,
            "DependBundleIDs": []
        },
        {
            "Address": "",
            "AssetPath": "Assets/Bundles/Font/Common/AlibabaSansJP.ttf",
            "AssetGUID": "",
            "AssetTags": [],
            "BundleID": 10,
            "DependBundleIDs": []
        },
        {
            "Address": "",
            "AssetPath": "Assets/Bundles/Font/Common/AlibabaSansKR SDF.asset",
            "AssetGUID": "",
            "AssetTags": [],
            "BundleID": 10,
            "DependBundleIDs": []
        },
        {
            "Address": "",
            "AssetPath": "Assets/Bundles/Font/Common/AlibabaSansKR.ttf",
            "AssetGUID": "",
            "AssetTags": [],
            "BundleID": 10,
            "DependBundleIDs": []
        },
        {
            "Address": "",
            "AssetPath": "Assets/Bundles/Font/TextMesh Pro/Fonts/chars.txt",
            "AssetGUID": "",
            "AssetTags": [],
            "BundleID": 11,
            "DependBundleIDs": []
        },
        {
            "Address": "",
            "AssetPath": "Assets/Bundles/Font/TextMesh Pro/Fonts/LiberationSans - OFL.txt",
            "AssetGUID": "",
            "AssetTags": [],
            "BundleID": 11,
            "DependBundleIDs": []
        },
        {
            "Address": "",
            "AssetPath": "Assets/Bundles/Font/TextMesh Pro/Fonts/LiberationSans.ttf",
            "AssetGUID": "",
            "AssetTags": [],
            "BundleID": 11,
            "DependBundleIDs": []
        },
        {
            "Address": "",
            "AssetPath": "Assets/Bundles/Font/TextMesh Pro/Resources/Fonts & Materials/LiberationSans SDF - Drop Shadow.mat",
            "AssetGUID": "",
            "AssetTags": [],
            "BundleID": 13,
            "DependBundleIDs": []
        },
        {
            "Address": "",
            "AssetPath": "Assets/Bundles/Font/TextMesh Pro/Resources/Fonts & Materials/LiberationSans SDF - Fallback.asset",
            "AssetGUID": "",
            "AssetTags": [],
            "BundleID": 13,
            "DependBundleIDs": []
        },
        {
            "Address": "",
            "AssetPath": "Assets/Bundles/Font/TextMesh Pro/Resources/Fonts & Materials/LiberationSans SDF - Outline.mat",
            "AssetGUID": "",
            "AssetTags": [],
            "BundleID": 13,
            "DependBundleIDs": []
        },
        {
            "Address": "",
            "AssetPath": "Assets/Bundles/Font/TextMesh Pro/Resources/Fonts & Materials/LiberationSans SDF.asset",
            "AssetGUID": "",
            "AssetTags": [],
            "BundleID": 13,
            "DependBundleIDs": []
        },
        {
            "Address": "",
            "AssetPath": "Assets/Bundles/Font/TextMesh Pro/Resources/Fonts & Materials/TextMeshMat.mat",
            "AssetGUID": "",
            "AssetTags": [],
            "BundleID": 13,
            "DependBundleIDs": []
        },
        {
            "Address": "",
            "AssetPath": "Assets/Bundles/Font/TextMesh Pro/Resources/LineBreaking Following Characters.txt",
            "AssetGUID": "",
            "AssetTags": [],
            "BundleID": 12,
            "DependBundleIDs": []
        },
        {
            "Address": "",
            "AssetPath": "Assets/Bundles/Font/TextMesh Pro/Resources/LineBreaking Leading Characters.txt",
            "AssetGUID": "",
            "AssetTags": [],
            "BundleID": 12,
            "DependBundleIDs": []
        },
        {
            "Address": "",
            "AssetPath": "Assets/Bundles/Font/TextMesh Pro/Resources/Sprite Assets/EmojiOne.asset",
            "AssetGUID": "",
            "AssetTags": [],
            "BundleID": 14,
            "DependBundleIDs": []
        },
        {
            "Address": "",
            "AssetPath": "Assets/Bundles/Font/TextMesh Pro/Resources/Style Sheets/Default Style Sheet.asset",
            "AssetGUID": "",
            "AssetTags": [],
            "BundleID": 15,
            "DependBundleIDs": []
        },
        {
            "Address": "",
            "AssetPath": "Assets/Bundles/Font/TextMesh Pro/Resources/TMP Settings.asset",
            "AssetGUID": "",
            "AssetTags": [],
            "BundleID": 12,
            "DependBundleIDs": []
        },
        {
            "Address": "",
            "AssetPath": "Assets/Bundles/Font/TextMesh Pro/Shaders/TMP_Bitmap.shader",
            "AssetGUID": "",
            "AssetTags": [],
            "BundleID": 43,
            "DependBundleIDs": []
        },
        {
            "Address": "",
            "AssetPath": "Assets/Bundles/Font/TextMesh Pro/Shaders/TMP_Bitmap-Custom-Atlas.shader",
            "AssetGUID": "",
            "AssetTags": [],
            "BundleID": 43,
            "DependBundleIDs": []
        },
        {
            "Address": "",
            "AssetPath": "Assets/Bundles/Font/TextMesh Pro/Shaders/TMP_Bitmap-Mobile.shader",
            "AssetGUID": "",
            "AssetTags": [],
            "BundleID": 43,
            "DependBundleIDs": []
        },
        {
            "Address": "",
            "AssetPath": "Assets/Bundles/Font/TextMesh Pro/Shaders/TMP_SDF Overlay.shader",
            "AssetGUID": "",
            "AssetTags": [],
            "BundleID": 43,
            "DependBundleIDs": []
        },
        {
            "Address": "",
            "AssetPath": "Assets/Bundles/Font/TextMesh Pro/Shaders/TMP_SDF SSD.shader",
            "AssetGUID": "",
            "AssetTags": [],
            "BundleID": 43,
            "DependBundleIDs": []
        },
        {
            "Address": "",
            "AssetPath": "Assets/Bundles/Font/TextMesh Pro/Shaders/TMP_SDF.shader",
            "AssetGUID": "",
            "AssetTags": [],
            "BundleID": 43,
            "DependBundleIDs": []
        },
        {
            "Address": "",
            "AssetPath": "Assets/Bundles/Font/TextMesh Pro/Shaders/TMP_SDF-HDRP LIT.shadergraph",
            "AssetGUID": "",
            "AssetTags": [],
            "BundleID": 43,
            "DependBundleIDs": []
        },
        {
            "Address": "",
            "AssetPath": "Assets/Bundles/Font/TextMesh Pro/Shaders/TMP_SDF-HDRP UNLIT.shadergraph",
            "AssetGUID": "",
            "AssetTags": [],
            "BundleID": 43,
            "DependBundleIDs": []
        },
        {
            "Address": "",
            "AssetPath": "Assets/Bundles/Font/TextMesh Pro/Shaders/TMP_SDF-Mobile Masking.shader",
            "AssetGUID": "",
            "AssetTags": [],
            "BundleID": 43,
            "DependBundleIDs": []
        },
        {
            "Address": "",
            "AssetPath": "Assets/Bundles/Font/TextMesh Pro/Shaders/TMP_SDF-Mobile Overlay.shader",
            "AssetGUID": "",
            "AssetTags": [],
            "BundleID": 43,
            "DependBundleIDs": []
        },
        {
            "Address": "",
            "AssetPath": "Assets/Bundles/Font/TextMesh Pro/Shaders/TMP_SDF-Mobile SSD.shader",
            "AssetGUID": "",
            "AssetTags": [],
            "BundleID": 43,
            "DependBundleIDs": []
        },
        {
            "Address": "",
            "AssetPath": "Assets/Bundles/Font/TextMesh Pro/Shaders/TMP_SDF-Mobile.shader",
            "AssetGUID": "",
            "AssetTags": [],
            "BundleID": 43,
            "DependBundleIDs": []
        },
        {
            "Address": "",
            "AssetPath": "Assets/Bundles/Font/TextMesh Pro/Shaders/TMP_SDF-Mobile-2-Pass.shader",
            "AssetGUID": "",
            "AssetTags": [],
            "BundleID": 43,
            "DependBundleIDs": []
        },
        {
            "Address": "",
            "AssetPath": "Assets/Bundles/Font/TextMesh Pro/Shaders/TMP_SDF-Surface.shader",
            "AssetGUID": "",
            "AssetTags": [],
            "BundleID": 43,
            "DependBundleIDs": []
        },
        {
            "Address": "",
            "AssetPath": "Assets/Bundles/Font/TextMesh Pro/Shaders/TMP_SDF-Surface-Mobile.shader",
            "AssetGUID": "",
            "AssetTags": [],
            "BundleID": 43,
            "DependBundleIDs": []
        },
        {
            "Address": "",
            "AssetPath": "Assets/Bundles/Font/TextMesh Pro/Shaders/TMP_SDF-URP Lit.shadergraph",
            "AssetGUID": "",
            "AssetTags": [],
            "BundleID": 43,
            "DependBundleIDs": []
        },
        {
            "Address": "",
            "AssetPath": "Assets/Bundles/Font/TextMesh Pro/Shaders/TMP_SDF-URP Unlit.shadergraph",
            "AssetGUID": "",
            "AssetTags": [],
            "BundleID": 43,
            "DependBundleIDs": []
        },
        {
            "Address": "",
            "AssetPath": "Assets/Bundles/Font/TextMesh Pro/Shaders/TMP_Sprite.shader",
            "AssetGUID": "",
            "AssetTags": [],
            "BundleID": 43,
            "DependBundleIDs": []
        },
        {
            "Address": "",
            "AssetPath": "Assets/Bundles/Font/TextMesh Pro/Sprites/EmojiOne Attribution.txt",
            "AssetGUID": "",
            "AssetTags": [],
            "BundleID": 16,
            "DependBundleIDs": []
        },
        {
            "Address": "",
            "AssetPath": "Assets/Bundles/Font/TextMesh Pro/Sprites/EmojiOne.json",
            "AssetGUID": "",
            "AssetTags": [],
            "BundleID": 16,
            "DependBundleIDs": []
        },
        {
            "Address": "",
            "AssetPath": "Assets/Bundles/Font/TextMesh Pro/Sprites/EmojiOne.png",
            "AssetGUID": "",
            "AssetTags": [],
            "BundleID": 16,
            "DependBundleIDs": []
        },
        {
            "Address": "",
            "AssetPath": "Assets/Bundles/HotfixDlls/Hotfix.bytes",
            "AssetGUID": "",
            "AssetTags": [],
            "BundleID": 17,
            "DependBundleIDs": []
        },
        {
            "Address": "",
            "AssetPath": "Assets/Bundles/HotfixDlls/HotfixFileList.txt",
            "AssetGUID": "",
            "AssetTags": [],
            "BundleID": 17,
            "DependBundleIDs": []
        },
        {
            "Address": "",
            "AssetPath": "Assets/Bundles/Image/home/gift.png",
            "AssetGUID": "",
            "AssetTags": [],
            "BundleID": 18,
            "DependBundleIDs": []
        },
        {
            "Address": "",
            "AssetPath": "Assets/Bundles/Image/home/good.png",
            "AssetGUID": "",
            "AssetTags": [],
            "BundleID": 18,
            "DependBundleIDs": []
        },
        {
            "Address": "",
            "AssetPath": "Assets/Bundles/Image/home/home_bg.png",
            "AssetGUID": "",
            "AssetTags": [],
            "BundleID": 18,
            "DependBundleIDs": []
        },
        {
            "Address": "",
            "AssetPath": "Assets/Bundles/Image/item/diamond1.png",
            "AssetGUID": "",
            "AssetTags": [],
            "BundleID": 19,
            "DependBundleIDs": []
        },
        {
            "Address": "",
            "AssetPath": "Assets/Bundles/Image/item/diamond10.png",
            "AssetGUID": "",
            "AssetTags": [],
            "BundleID": 19,
            "DependBundleIDs": []
        },
        {
            "Address": "",
            "AssetPath": "Assets/Bundles/Image/item/diamond11.png",
            "AssetGUID": "",
            "AssetTags": [],
            "BundleID": 19,
            "DependBundleIDs": []
        },
        {
            "Address": "",
            "AssetPath": "Assets/Bundles/Image/item/diamond2.png",
            "AssetGUID": "",
            "AssetTags": [],
            "BundleID": 19,
            "DependBundleIDs": []
        },
        {
            "Address": "",
            "AssetPath": "Assets/Bundles/Image/item/diamond3.png",
            "AssetGUID": "",
            "AssetTags": [],
            "BundleID": 19,
            "DependBundleIDs": []
        },
        {
            "Address": "",
            "AssetPath": "Assets/Bundles/Image/item/diamond4.png",
            "AssetGUID": "",
            "AssetTags": [],
            "BundleID": 19,
            "DependBundleIDs": []
        },
        {
            "Address": "",
            "AssetPath": "Assets/Bundles/Image/item/diamond5.png",
            "AssetGUID": "",
            "AssetTags": [],
            "BundleID": 19,
            "DependBundleIDs": []
        },
        {
            "Address": "",
            "AssetPath": "Assets/Bundles/Image/item/diamond6.png",
            "AssetGUID": "",
            "AssetTags": [],
            "BundleID": 19,
            "DependBundleIDs": []
        },
        {
            "Address": "",
            "AssetPath": "Assets/Bundles/Image/item/diamond7.png",
            "AssetGUID": "",
            "AssetTags": [],
            "BundleID": 19,
            "DependBundleIDs": []
        },
        {
            "Address": "",
            "AssetPath": "Assets/Bundles/Image/item/diamond8.png",
            "AssetGUID": "",
            "AssetTags": [],
            "BundleID": 19,
            "DependBundleIDs": []
        },
        {
            "Address": "",
            "AssetPath": "Assets/Bundles/Image/item/diamond9.png",
            "AssetGUID": "",
            "AssetTags": [],
            "BundleID": 19,
            "DependBundleIDs": []
        },
        {
            "Address": "",
            "AssetPath": "Assets/Bundles/Image/item/goods_bg1.png",
            "AssetGUID": "",
            "AssetTags": [],
            "BundleID": 19,
            "DependBundleIDs": []
        },
        {
            "Address": "",
            "AssetPath": "Assets/Bundles/Language/ChineseSimplified.bytes",
            "AssetGUID": "",
            "AssetTags": [],
            "BundleID": 20,
            "DependBundleIDs": []
        },
        {
            "Address": "",
            "AssetPath": "Assets/Bundles/Language/ChineseSimplified.json",
            "AssetGUID": "",
            "AssetTags": [],
            "BundleID": 20,
            "DependBundleIDs": []
        },
        {
            "Address": "",
            "AssetPath": "Assets/Bundles/Language/ChineseTraditional.bytes",
            "AssetGUID": "",
            "AssetTags": [],
            "BundleID": 20,
            "DependBundleIDs": []
        },
        {
            "Address": "",
            "AssetPath": "Assets/Bundles/Language/ChineseTraditional.json",
            "AssetGUID": "",
            "AssetTags": [],
            "BundleID": 20,
            "DependBundleIDs": []
        },
        {
            "Address": "",
            "AssetPath": "Assets/Bundles/Language/English.bytes",
            "AssetGUID": "",
            "AssetTags": [],
            "BundleID": 20,
            "DependBundleIDs": []
        },
        {
            "Address": "",
            "AssetPath": "Assets/Bundles/Language/English.json",
            "AssetGUID": "",
            "AssetTags": [],
            "BundleID": 20,
            "DependBundleIDs": []
        },
        {
            "Address": "",
            "AssetPath": "Assets/Bundles/Language/Japanese.bytes",
            "AssetGUID": "",
            "AssetTags": [],
            "BundleID": 20,
            "DependBundleIDs": []
        },
        {
            "Address": "",
            "AssetPath": "Assets/Bundles/Language/Japanese.json",
            "AssetGUID": "",
            "AssetTags": [],
            "BundleID": 20,
            "DependBundleIDs": []
        },
        {
            "Address": "",
            "AssetPath": "Assets/Bundles/Language/Korean.bytes",
            "AssetGUID": "",
            "AssetTags": [],
            "BundleID": 20,
            "DependBundleIDs": []
        },
        {
            "Address": "",
            "AssetPath": "Assets/Bundles/Language/Korean.json",
            "AssetGUID": "",
            "AssetTags": [],
            "BundleID": 20,
            "DependBundleIDs": []
        },
        {
            "Address": "",
            "AssetPath": "Assets/Bundles/Materials/AiSmall.mat",
            "AssetGUID": "",
            "AssetTags": [],
            "BundleID": 21,
            "DependBundleIDs": []
        },
        {
            "Address": "",
            "AssetPath": "Assets/Bundles/Materials/AreaEdge.mat",
            "AssetGUID": "",
            "AssetTags": [],
            "BundleID": 21,
            "DependBundleIDs": []
        },
        {
            "Address": "",
            "AssetPath": "Assets/Bundles/Materials/circle.mat",
            "AssetGUID": "",
            "AssetTags": [],
            "BundleID": 21,
            "DependBundleIDs": []
        },
        {
            "Address": "",
            "AssetPath": "Assets/Bundles/Materials/circle.png",
            "AssetGUID": "",
            "AssetTags": [],
            "BundleID": 21,
            "DependBundleIDs": []
        },
        {
            "Address": "",
            "AssetPath": "Assets/Bundles/Materials/Common/UIHighLight.mat",
            "AssetGUID": "",
            "AssetTags": [],
            "BundleID": 22,
            "DependBundleIDs": []
        },
        {
            "Address": "",
            "AssetPath": "Assets/Bundles/Materials/Common/UIMaskBg.mat",
            "AssetGUID": "",
            "AssetTags": [],
            "BundleID": 22,
            "DependBundleIDs": []
        },
        {
            "Address": "",
            "AssetPath": "Assets/Bundles/Materials/Common/UIMasked.mat",
            "AssetGUID": "",
            "AssetTags": [],
            "BundleID": 22,
            "DependBundleIDs": []
        },
        {
            "Address": "",
            "AssetPath": "Assets/Bundles/Materials/FireFx.mat",
            "AssetGUID": "",
            "AssetTags": [],
            "BundleID": 21,
            "DependBundleIDs": []
        },
        {
            "Address": "",
            "AssetPath": "Assets/Bundles/Materials/Ground.mat",
            "AssetGUID": "",
            "AssetTags": [],
            "BundleID": 21,
            "DependBundleIDs": []
        },
        {
            "Address": "",
            "AssetPath": "Assets/Bundles/Materials/Mat_ActionPropsPack_vol3_standardShader_vol.3.mat",
            "AssetGUID": "",
            "AssetTags": [],
            "BundleID": 21,
            "DependBundleIDs": []
        },
        {
            "Address": "",
            "AssetPath": "Assets/Bundles/Materials/pathLine.png",
            "AssetGUID": "",
            "AssetTags": [],
            "BundleID": 21,
            "DependBundleIDs": []
        },
        {
            "Address": "",
            "AssetPath": "Assets/Bundles/Materials/Player.mat",
            "AssetGUID": "",
            "AssetTags": [],
            "BundleID": 21,
            "DependBundleIDs": []
        },
        {
            "Address": "",
            "AssetPath": "Assets/Bundles/Materials/TrialMat.mat",
            "AssetGUID": "",
            "AssetTags": [],
            "BundleID": 21,
            "DependBundleIDs": []
        },
        {
            "Address": "",
            "AssetPath": "Assets/Bundles/Models/AISmall.fbx",
            "AssetGUID": "",
            "AssetTags": [],
            "BundleID": 23,
            "DependBundleIDs": []
        },
        {
            "Address": "",
            "AssetPath": "Assets/Bundles/Models/Pistol05.fbx",
            "AssetGUID": "",
            "AssetTags": [],
            "BundleID": 23,
            "DependBundleIDs": []
        },
        {
            "Address": "",
            "AssetPath": "Assets/Bundles/Models/Stickman_heads_sphere.fbx",
            "AssetGUID": "",
            "AssetTags": [],
            "BundleID": 23,
            "DependBundleIDs": []
        },
        {
            "Address": "",
            "AssetPath": "Assets/Bundles/Prefabs/Core/GFExtension.prefab",
            "AssetGUID": "",
            "AssetTags": [],
            "BundleID": 24,
            "DependBundleIDs": []
        },
        {
            "Address": "",
            "AssetPath": "Assets/Bundles/Prefabs/Entity/Bullet.prefab",
            "AssetGUID": "",
            "AssetTags": [],
            "BundleID": 25,
            "DependBundleIDs": []
        },
        {
            "Address": "",
            "AssetPath": "Assets/Bundles/Prefabs/Entity/Effect/BloodExplosion.prefab",
            "AssetGUID": "",
            "AssetTags": [],
            "BundleID": 26,
            "DependBundleIDs": []
        },
        {
            "Address": "",
            "AssetPath": "Assets/Bundles/Prefabs/Entity/Effect/FireFx.prefab",
            "AssetGUID": "",
            "AssetTags": [],
            "BundleID": 26,
            "DependBundleIDs": []
        },
        {
            "Address": "",
            "AssetPath": "Assets/Bundles/Prefabs/Entity/Effect/MoneyText.prefab",
            "AssetGUID": "",
            "AssetTags": [],
            "BundleID": 26,
            "DependBundleIDs": []
        },
        {
            "Address": "",
            "AssetPath": "Assets/Bundles/Prefabs/Entity/Effect/Trail.prefab",
            "AssetGUID": "",
            "AssetTags": [],
            "BundleID": 26,
            "DependBundleIDs": []
        },
        {
            "Address": "",
            "AssetPath": "Assets/Bundles/Prefabs/Entity/Enemy.prefab",
            "AssetGUID": "",
            "AssetTags": [],
            "BundleID": 25,
            "DependBundleIDs": []
        },
        {
            "Address": "",
            "AssetPath": "Assets/Bundles/Prefabs/Entity/EnemyLv2.prefab",
            "AssetGUID": "",
            "AssetTags": [],
            "BundleID": 25,
            "DependBundleIDs": []
        },
        {
            "Address": "",
            "AssetPath": "Assets/Bundles/Prefabs/Entity/EnemyLv3.prefab",
            "AssetGUID": "",
            "AssetTags": [],
            "BundleID": 25,
            "DependBundleIDs": []
        },
        {
            "Address": "",
            "AssetPath": "Assets/Bundles/Prefabs/Entity/Gun.prefab",
            "AssetGUID": "",
            "AssetTags": [],
            "BundleID": 25,
            "DependBundleIDs": []
        },
        {
            "Address": "",
            "AssetPath": "Assets/Bundles/Prefabs/Entity/Lv_1.prefab",
            "AssetGUID": "",
            "AssetTags": [],
            "BundleID": 25,
            "DependBundleIDs": []
        },
        {
            "Address": "",
            "AssetPath": "Assets/Bundles/Prefabs/Entity/MyPlayer.prefab",
            "AssetGUID": "",
            "AssetTags": [],
            "BundleID": 25,
            "DependBundleIDs": []
        },
        {
            "Address": "",
            "AssetPath": "Assets/Bundles/Prefabs/UI/CommonDialog.prefab",
            "AssetGUID": "",
            "AssetTags": [],
            "BundleID": 27,
            "DependBundleIDs": []
        },
        {
            "Address": "",
            "AssetPath": "Assets/Bundles/Prefabs/UI/GameOverUIForm.prefab",
            "AssetGUID": "",
            "AssetTags": [],
            "BundleID": 27,
            "DependBundleIDs": []
        },
        {
            "Address": "",
            "AssetPath": "Assets/Bundles/Prefabs/UI/GameUIForm.prefab",
            "AssetGUID": "",
            "AssetTags": [],
            "BundleID": 27,
            "DependBundleIDs": []
        },
        {
            "Address": "",
            "AssetPath": "Assets/Bundles/Prefabs/UI/Items/LanguageToggle.prefab",
            "AssetGUID": "",
            "AssetTags": [],
            "BundleID": 28,
            "DependBundleIDs": []
        },
        {
            "Address": "",
            "AssetPath": "Assets/Bundles/Prefabs/UI/LanguagesDialog.prefab",
            "AssetGUID": "",
            "AssetTags": [],
            "BundleID": 27,
            "DependBundleIDs": []
        },
        {
            "Address": "",
            "AssetPath": "Assets/Bundles/Prefabs/UI/MenuUIForm.prefab",
            "AssetGUID": "",
            "AssetTags": [],
            "BundleID": 27,
            "DependBundleIDs": []
        },
        {
            "Address": "",
            "AssetPath": "Assets/Bundles/Prefabs/UI/RatingDialog.prefab",
            "AssetGUID": "",
            "AssetTags": [],
            "BundleID": 27,
            "DependBundleIDs": []
        },
        {
            "Address": "",
            "AssetPath": "Assets/Bundles/Prefabs/UI/SettingDialog.prefab",
            "AssetGUID": "",
            "AssetTags": [],
            "BundleID": 27,
            "DependBundleIDs": []
        },
        {
            "Address": "",
            "AssetPath": "Assets/Bundles/Prefabs/UI/ShopUIForm.prefab",
            "AssetGUID": "",
            "AssetTags": [],
            "BundleID": 27,
            "DependBundleIDs": []
        },
        {
            "Address": "",
            "AssetPath": "Assets/Bundles/Prefabs/UI/TipsDialog.prefab",
            "AssetGUID": "",
            "AssetTags": [],
            "BundleID": 27,
            "DependBundleIDs": []
        },
        {
            "Address": "",
            "AssetPath": "Assets/Bundles/Prefabs/UI/ToastTips.prefab",
            "AssetGUID": "",
            "AssetTags": [],
            "BundleID": 27,
            "DependBundleIDs": []
        },
        {
            "Address": "",
            "AssetPath": "Assets/Bundles/Prefabs/UI/Topbar.prefab",
            "AssetGUID": "",
            "AssetTags": [],
            "BundleID": 27,
            "DependBundleIDs": []
        },
        {
            "Address": "",
            "AssetPath": "Assets/Bundles/Scenes/Game.unity",
            "AssetGUID": "",
            "AssetTags": [],
            "BundleID": 29,
            "DependBundleIDs": []
        },
        {
            "Address": "",
            "AssetPath": "Assets/Bundles/ScriptableAssets/Core/AppConfigs.asset",
            "AssetGUID": "",
            "AssetTags": [],
            "BundleID": 30,
            "DependBundleIDs": []
        },
        {
            "Address": "",
            "AssetPath": "Assets/Bundles/Shader/ASE/FastLit.shader",
            "AssetGUID": "",
            "AssetTags": [],
            "BundleID": 43,
            "DependBundleIDs": []
        },
        {
            "Address": "",
            "AssetPath": "Assets/Bundles/Shader/TextMeshFont.shader",
            "AssetGUID": "",
            "AssetTags": [],
            "BundleID": 43,
            "DependBundleIDs": []
        },
        {
            "Address": "",
            "AssetPath": "Assets/Bundles/Sprites/avatar/0.png",
            "AssetGUID": "",
            "AssetTags": [],
            "BundleID": 31,
            "DependBundleIDs": []
        },
        {
            "Address": "",
            "AssetPath": "Assets/Bundles/Sprites/avatar/1.png",
            "AssetGUID": "",
            "AssetTags": [],
            "BundleID": 31,
            "DependBundleIDs": []
        },
        {
            "Address": "",
            "AssetPath": "Assets/Bundles/Sprites/avatar/10.png",
            "AssetGUID": "",
            "AssetTags": [],
            "BundleID": 31,
            "DependBundleIDs": []
        },
        {
            "Address": "",
            "AssetPath": "Assets/Bundles/Sprites/avatar/11.png",
            "AssetGUID": "",
            "AssetTags": [],
            "BundleID": 31,
            "DependBundleIDs": []
        },
        {
            "Address": "",
            "AssetPath": "Assets/Bundles/Sprites/avatar/12.png",
            "AssetGUID": "",
            "AssetTags": [],
            "BundleID": 31,
            "DependBundleIDs": []
        },
        {
            "Address": "",
            "AssetPath": "Assets/Bundles/Sprites/avatar/13.png",
            "AssetGUID": "",
            "AssetTags": [],
            "BundleID": 31,
            "DependBundleIDs": []
        },
        {
            "Address": "",
            "AssetPath": "Assets/Bundles/Sprites/avatar/14.png",
            "AssetGUID": "",
            "AssetTags": [],
            "BundleID": 31,
            "DependBundleIDs": []
        },
        {
            "Address": "",
            "AssetPath": "Assets/Bundles/Sprites/avatar/15.png",
            "AssetGUID": "",
            "AssetTags": [],
            "BundleID": 31,
            "DependBundleIDs": []
        },
        {
            "Address": "",
            "AssetPath": "Assets/Bundles/Sprites/avatar/16.png",
            "AssetGUID": "",
            "AssetTags": [],
            "BundleID": 31,
            "DependBundleIDs": []
        },
        {
            "Address": "",
            "AssetPath": "Assets/Bundles/Sprites/avatar/17.png",
            "AssetGUID": "",
            "AssetTags": [],
            "BundleID": 31,
            "DependBundleIDs": []
        },
        {
            "Address": "",
            "AssetPath": "Assets/Bundles/Sprites/avatar/18.png",
            "AssetGUID": "",
            "AssetTags": [],
            "BundleID": 31,
            "DependBundleIDs": []
        },
        {
            "Address": "",
            "AssetPath": "Assets/Bundles/Sprites/avatar/19.png",
            "AssetGUID": "",
            "AssetTags": [],
            "BundleID": 31,
            "DependBundleIDs": []
        },
        {
            "Address": "",
            "AssetPath": "Assets/Bundles/Sprites/avatar/2.png",
            "AssetGUID": "",
            "AssetTags": [],
            "BundleID": 31,
            "DependBundleIDs": []
        },
        {
            "Address": "",
            "AssetPath": "Assets/Bundles/Sprites/avatar/20.png",
            "AssetGUID": "",
            "AssetTags": [],
            "BundleID": 31,
            "DependBundleIDs": []
        },
        {
            "Address": "",
            "AssetPath": "Assets/Bundles/Sprites/avatar/21.png",
            "AssetGUID": "",
            "AssetTags": [],
            "BundleID": 31,
            "DependBundleIDs": []
        },
        {
            "Address": "",
            "AssetPath": "Assets/Bundles/Sprites/avatar/22.png",
            "AssetGUID": "",
            "AssetTags": [],
            "BundleID": 31,
            "DependBundleIDs": []
        },
        {
            "Address": "",
            "AssetPath": "Assets/Bundles/Sprites/avatar/23.png",
            "AssetGUID": "",
            "AssetTags": [],
            "BundleID": 31,
            "DependBundleIDs": []
        },
        {
            "Address": "",
            "AssetPath": "Assets/Bundles/Sprites/avatar/24.png",
            "AssetGUID": "",
            "AssetTags": [],
            "BundleID": 31,
            "DependBundleIDs": []
        },
        {
            "Address": "",
            "AssetPath": "Assets/Bundles/Sprites/avatar/25.png",
            "AssetGUID": "",
            "AssetTags": [],
            "BundleID": 31,
            "DependBundleIDs": []
        },
        {
            "Address": "",
            "AssetPath": "Assets/Bundles/Sprites/avatar/26.png",
            "AssetGUID": "",
            "AssetTags": [],
            "BundleID": 31,
            "DependBundleIDs": []
        },
        {
            "Address": "",
            "AssetPath": "Assets/Bundles/Sprites/avatar/27.png",
            "AssetGUID": "",
            "AssetTags": [],
            "BundleID": 31,
            "DependBundleIDs": []
        },
        {
            "Address": "",
            "AssetPath": "Assets/Bundles/Sprites/avatar/28.png",
            "AssetGUID": "",
            "AssetTags": [],
            "BundleID": 31,
            "DependBundleIDs": []
        },
        {
            "Address": "",
            "AssetPath": "Assets/Bundles/Sprites/avatar/29.png",
            "AssetGUID": "",
            "AssetTags": [],
            "BundleID": 31,
            "DependBundleIDs": []
        },
        {
            "Address": "",
            "AssetPath": "Assets/Bundles/Sprites/avatar/3.png",
            "AssetGUID": "",
            "AssetTags": [],
            "BundleID": 31,
            "DependBundleIDs": []
        },
        {
            "Address": "",
            "AssetPath": "Assets/Bundles/Sprites/avatar/30.png",
            "AssetGUID": "",
            "AssetTags": [],
            "BundleID": 31,
            "DependBundleIDs": []
        },
        {
            "Address": "",
            "AssetPath": "Assets/Bundles/Sprites/avatar/31.png",
            "AssetGUID": "",
            "AssetTags": [],
            "BundleID": 31,
            "DependBundleIDs": []
        },
        {
            "Address": "",
            "AssetPath": "Assets/Bundles/Sprites/avatar/32.png",
            "AssetGUID": "",
            "AssetTags": [],
            "BundleID": 31,
            "DependBundleIDs": []
        },
        {
            "Address": "",
            "AssetPath": "Assets/Bundles/Sprites/avatar/33.png",
            "AssetGUID": "",
            "AssetTags": [],
            "BundleID": 31,
            "DependBundleIDs": []
        },
        {
            "Address": "",
            "AssetPath": "Assets/Bundles/Sprites/avatar/34.png",
            "AssetGUID": "",
            "AssetTags": [],
            "BundleID": 31,
            "DependBundleIDs": []
        },
        {
            "Address": "",
            "AssetPath": "Assets/Bundles/Sprites/avatar/35.png",
            "AssetGUID": "",
            "AssetTags": [],
            "BundleID": 31,
            "DependBundleIDs": []
        },
        {
            "Address": "",
            "AssetPath": "Assets/Bundles/Sprites/avatar/36.png",
            "AssetGUID": "",
            "AssetTags": [],
            "BundleID": 31,
            "DependBundleIDs": []
        },
        {
            "Address": "",
            "AssetPath": "Assets/Bundles/Sprites/avatar/37.png",
            "AssetGUID": "",
            "AssetTags": [],
            "BundleID": 31,
            "DependBundleIDs": []
        },
        {
            "Address": "",
            "AssetPath": "Assets/Bundles/Sprites/avatar/38.png",
            "AssetGUID": "",
            "AssetTags": [],
            "BundleID": 31,
            "DependBundleIDs": []
        },
        {
            "Address": "",
            "AssetPath": "Assets/Bundles/Sprites/avatar/39.png",
            "AssetGUID": "",
            "AssetTags": [],
            "BundleID": 31,
            "DependBundleIDs": []
        },
        {
            "Address": "",
            "AssetPath": "Assets/Bundles/Sprites/avatar/4.png",
            "AssetGUID": "",
            "AssetTags": [],
            "BundleID": 31,
            "DependBundleIDs": []
        },
        {
            "Address": "",
            "AssetPath": "Assets/Bundles/Sprites/avatar/40.png",
            "AssetGUID": "",
            "AssetTags": [],
            "BundleID": 31,
            "DependBundleIDs": []
        },
        {
            "Address": "",
            "AssetPath": "Assets/Bundles/Sprites/avatar/41.png",
            "AssetGUID": "",
            "AssetTags": [],
            "BundleID": 31,
            "DependBundleIDs": []
        },
        {
            "Address": "",
            "AssetPath": "Assets/Bundles/Sprites/avatar/42.png",
            "AssetGUID": "",
            "AssetTags": [],
            "BundleID": 31,
            "DependBundleIDs": []
        },
        {
            "Address": "",
            "AssetPath": "Assets/Bundles/Sprites/avatar/43.png",
            "AssetGUID": "",
            "AssetTags": [],
            "BundleID": 31,
            "DependBundleIDs": []
        },
        {
            "Address": "",
            "AssetPath": "Assets/Bundles/Sprites/avatar/44.png",
            "AssetGUID": "",
            "AssetTags": [],
            "BundleID": 31,
            "DependBundleIDs": []
        },
        {
            "Address": "",
            "AssetPath": "Assets/Bundles/Sprites/avatar/45.png",
            "AssetGUID": "",
            "AssetTags": [],
            "BundleID": 31,
            "DependBundleIDs": []
        },
        {
            "Address": "",
            "AssetPath": "Assets/Bundles/Sprites/avatar/46.png",
            "AssetGUID": "",
            "AssetTags": [],
            "BundleID": 31,
            "DependBundleIDs": []
        },
        {
            "Address": "",
            "AssetPath": "Assets/Bundles/Sprites/avatar/47.png",
            "AssetGUID": "",
            "AssetTags": [],
            "BundleID": 31,
            "DependBundleIDs": []
        },
        {
            "Address": "",
            "AssetPath": "Assets/Bundles/Sprites/avatar/48.png",
            "AssetGUID": "",
            "AssetTags": [],
            "BundleID": 31,
            "DependBundleIDs": []
        },
        {
            "Address": "",
            "AssetPath": "Assets/Bundles/Sprites/avatar/49.png",
            "AssetGUID": "",
            "AssetTags": [],
            "BundleID": 31,
            "DependBundleIDs": []
        },
        {
            "Address": "",
            "AssetPath": "Assets/Bundles/Sprites/avatar/5.png",
            "AssetGUID": "",
            "AssetTags": [],
            "BundleID": 31,
            "DependBundleIDs": []
        },
        {
            "Address": "",
            "AssetPath": "Assets/Bundles/Sprites/avatar/50.png",
            "AssetGUID": "",
            "AssetTags": [],
            "BundleID": 31,
            "DependBundleIDs": []
        },
        {
            "Address": "",
            "AssetPath": "Assets/Bundles/Sprites/avatar/6.png",
            "AssetGUID": "",
            "AssetTags": [],
            "BundleID": 31,
            "DependBundleIDs": []
        },
        {
            "Address": "",
            "AssetPath": "Assets/Bundles/Sprites/avatar/7.png",
            "AssetGUID": "",
            "AssetTags": [],
            "BundleID": 31,
            "DependBundleIDs": []
        },
        {
            "Address": "",
            "AssetPath": "Assets/Bundles/Sprites/avatar/8.png",
            "AssetGUID": "",
            "AssetTags": [],
            "BundleID": 31,
            "DependBundleIDs": []
        },
        {
            "Address": "",
            "AssetPath": "Assets/Bundles/Sprites/avatar/9.png",
            "AssetGUID": "",
            "AssetTags": [],
            "BundleID": 31,
            "DependBundleIDs": []
        },
        {
            "Address": "",
            "AssetPath": "Assets/Bundles/Sprites/Common/Circle.png",
            "AssetGUID": "",
            "AssetTags": [],
            "BundleID": 32,
            "DependBundleIDs": []
        },
        {
            "Address": "",
            "AssetPath": "Assets/Bundles/Sprites/UI/IconMisc/Icon_Check03_s.png",
            "AssetGUID": "",
            "AssetTags": [],
            "BundleID": 33,
            "DependBundleIDs": []
        },
        {
            "Address": "",
            "AssetPath": "Assets/Bundles/Sprites/UI/IconMisc/Icon_Close02.png",
            "AssetGUID": "",
            "AssetTags": [],
            "BundleID": 33,
            "DependBundleIDs": []
        },
        {
            "Address": "",
            "AssetPath": "Assets/Bundles/Sprites/UI/IconMisc/Icon_Setting.png",
            "AssetGUID": "",
            "AssetTags": [],
            "BundleID": 33,
            "DependBundleIDs": []
        },
        {
            "Address": "",
            "AssetPath": "Assets/Bundles/Sprites/UI/IconMisc/Icon_Star_Off.png",
            "AssetGUID": "",
            "AssetTags": [],
            "BundleID": 33,
            "DependBundleIDs": []
        },
        {
            "Address": "",
            "AssetPath": "Assets/Bundles/Sprites/UI/IconMisc/Icon_Star_On.png",
            "AssetGUID": "",
            "AssetTags": [],
            "BundleID": 33,
            "DependBundleIDs": []
        },
        {
            "Address": "",
            "AssetPath": "Assets/Bundles/Sprites/UI/Toast/ToastMessage_Bg_Gray.png",
            "AssetGUID": "",
            "AssetTags": [],
            "BundleID": 34,
            "DependBundleIDs": []
        },
        {
            "Address": "",
            "AssetPath": "Assets/Bundles/Sprites/UI/Toast/ToastMessage_Bg_Green.png",
            "AssetGUID": "",
            "AssetTags": [],
            "BundleID": 34,
            "DependBundleIDs": []
        },
        {
            "Address": "",
            "AssetPath": "Assets/Bundles/Sprites/UI/Toast/ToastMessage_Bg_Red.png",
            "AssetGUID": "",
            "AssetTags": [],
            "BundleID": 34,
            "DependBundleIDs": []
        },
        {
            "Address": "",
            "AssetPath": "Assets/Bundles/Sprites/UI/Toast/ToastMessage_Bg_White.png",
            "AssetGUID": "",
            "AssetTags": [],
            "BundleID": 34,
            "DependBundleIDs": []
        },
        {
            "Address": "",
            "AssetPath": "Assets/Bundles/Sprites/UI/Toast/ToastMessage_Bg_Yellow.png",
            "AssetGUID": "",
            "AssetTags": [],
            "BundleID": 34,
            "DependBundleIDs": []
        },
        {
            "Address": "",
            "AssetPath": "Assets/Bundles/Sprites/UI/Toast/ToastMessage_Gradient.png",
            "AssetGUID": "",
            "AssetTags": [],
            "BundleID": 34,
            "DependBundleIDs": []
        },
        {
            "Address": "",
            "AssetPath": "Assets/Bundles/Sprites/UI/Toast/ToastMessage_Light1.png",
            "AssetGUID": "",
            "AssetTags": [],
            "BundleID": 34,
            "DependBundleIDs": []
        },
        {
            "Address": "",
            "AssetPath": "Assets/Bundles/Sprites/UI/Toast/ToastMessage_Light2.png",
            "AssetGUID": "",
            "AssetTags": [],
            "BundleID": 34,
            "DependBundleIDs": []
        },
        {
            "Address": "",
            "AssetPath": "Assets/Bundles/Textures/magic_line.png",
            "AssetGUID": "",
            "AssetTags": [],
            "BundleID": 35,
            "DependBundleIDs": []
        },
        {
            "Address": "",
            "AssetPath": "Assets/Bundles/UI/UIBag/UIBag_fui.bytes",
            "AssetGUID": "",
            "AssetTags": [],
            "BundleID": 36,
            "DependBundleIDs": []
        },
        {
            "Address": "",
            "AssetPath": "Assets/Bundles/UI/UICommon/UICommon_atlas0.png",
            "AssetGUID": "",
            "AssetTags": [],
            "BundleID": 37,
            "DependBundleIDs": []
        },
        {
            "Address": "",
            "AssetPath": "Assets/Bundles/UI/UICommon/UICommon_fui.bytes",
            "AssetGUID": "",
            "AssetTags": [],
            "BundleID": 37,
            "DependBundleIDs": []
        },
        {
            "Address": "",
            "AssetPath": "Assets/Bundles/UI/UICommonAvatar/UICommonAvatar_atlas0.png",
            "AssetGUID": "",
            "AssetTags": [],
            "BundleID": 38,
            "DependBundleIDs": []
        },
        {
            "Address": "",
            "AssetPath": "Assets/Bundles/UI/UICommonAvatar/UICommonAvatar_fui.bytes",
            "AssetGUID": "",
            "AssetTags": [],
            "BundleID": 38,
            "DependBundleIDs": []
        },
        {
            "Address": "",
            "AssetPath": "Assets/Bundles/UI/UILoading/UILoading_fui.bytes",
            "AssetGUID": "",
            "AssetTags": [],
            "BundleID": 39,
            "DependBundleIDs": []
        },
        {
            "Address": "",
            "AssetPath": "Assets/Bundles/UI/UILogin/background_05_sample_00_1920.png",
            "AssetGUID": "",
            "AssetTags": [],
            "BundleID": 40,
            "DependBundleIDs": []
        },
        {
            "Address": "",
            "AssetPath": "Assets/Bundles/UI/UILogin/UILogin.prefab",
            "AssetGUID": "",
            "AssetTags": [],
            "BundleID": 40,
            "DependBundleIDs": []
        },
        {
            "Address": "",
            "AssetPath": "Assets/Bundles/UI/UILogin/UILogin_atlas0.png",
            "AssetGUID": "",
            "AssetTags": [],
            "BundleID": 40,
            "DependBundleIDs": []
        },
        {
            "Address": "",
            "AssetPath": "Assets/Bundles/UI/UILogin/UILogin_fui.bytes",
            "AssetGUID": "",
            "AssetTags": [],
            "BundleID": 40,
            "DependBundleIDs": []
        },
        {
            "Address": "",
            "AssetPath": "Assets/Bundles/UI/UILogin/UIPlayerCreate.prefab",
            "AssetGUID": "",
            "AssetTags": [],
            "BundleID": 40,
            "DependBundleIDs": []
        },
        {
            "Address": "",
            "AssetPath": "Assets/Bundles/UI/UILogin/UIPlayerList.prefab",
            "AssetGUID": "",
            "AssetTags": [],
            "BundleID": 40,
            "DependBundleIDs": []
        },
        {
            "Address": "",
            "AssetPath": "Assets/Bundles/UI/UILogin/UIPlayerListItem.prefab",
            "AssetGUID": "",
            "AssetTags": [],
            "BundleID": 40,
            "DependBundleIDs": []
        },
        {
            "Address": "",
            "AssetPath": "Assets/Bundles/UI/UIMain/UIMain.prefab",
            "AssetGUID": "",
            "AssetTags": [],
            "BundleID": 41,
            "DependBundleIDs": []
        },
        {
            "Address": "",
            "AssetPath": "Assets/Bundles/UI/UIMain/UIMain_atlas0.png",
            "AssetGUID": "",
            "AssetTags": [],
            "BundleID": 41,
            "DependBundleIDs": []
        },
        {
            "Address": "",
            "AssetPath": "Assets/Bundles/UI/UIMain/UIMain_fui.bytes",
            "AssetGUID": "",
            "AssetTags": [],
            "BundleID": 41,
            "DependBundleIDs": []
        },
        {
            "Address": "",
            "AssetPath": "Assets/Bundles/UI/UIPlayer/UIPlayer_fui.bytes",
            "AssetGUID": "",
            "AssetTags": [],
            "BundleID": 42,
            "DependBundleIDs": []
        }
    ],
    "BundleList": [
        {
            "BundleName": "defaultpackage_assets_aaagame_datatable.bundle",
            "UnityCRC": 0,
            "FileHash": "e5113be19df99cbf9bac09fc9dd783ba",
            "FileCRC": 0,
            "FileSize": 2744,
            "Encrypted": false,
            "Tags": [],
            "DependBundleIDs": []
        },
        {
            "BundleName": "defaultpackage_assets_aaagame_datatable_core.bundle",
            "UnityCRC": 0,
            "FileHash": "a2730050cd366218bcd1c4fc81a0b3a1",
            "FileCRC": 0,
            "FileSize": 2852,
            "Encrypted": false,
            "Tags": [],
            "DependBundleIDs": []
        },
        {
            "BundleName": "defaultpackage_assets_aaagame_scene.bundle",
            "UnityCRC": 0,
            "FileHash": "4c8d538b5fa205d84837c02806ac5916",
            "FileCRC": 0,
            "FileSize": 103850,
            "Encrypted": false,
            "Tags": [],
            "DependBundleIDs": []
        },
        {
            "BundleName": "defaultpackage_assets_aaagame_scripts.bundle",
            "UnityCRC": 0,
            "FileHash": "84b9be4c4116ee44eaeedc4e005ed5d7",
            "FileCRC": 0,
            "FileSize": 1568,
            "Encrypted": false,
            "Tags": [],
            "DependBundleIDs": []
        },
        {
            "BundleName": "defaultpackage_assets_aaagame_scriptsbuiltin_runtime.bundle",
            "UnityCRC": 0,
            "FileHash": "890eca00a085ce164509aedd828acf0a",
            "FileCRC": 0,
            "FileSize": 1661,
            "Encrypted": false,
            "Tags": [],
            "DependBundleIDs": []
        },
        {
            "BundleName": "defaultpackage_assets_bundles_animation.bundle",
            "UnityCRC": 0,
            "FileHash": "7df33da334cdecdcd65f6ef0ba034c99",
            "FileCRC": 0,
            "FileSize": 2371400,
            "Encrypted": false,
            "Tags": [],
            "DependBundleIDs": []
        },
        {
            "BundleName": "defaultpackage_assets_bundles_animation_ui.bundle",
            "UnityCRC": 0,
            "FileHash": "f5e023149d7e1c6a0dd6783682bd3c59",
            "FileCRC": 0,
            "FileSize": 103704,
            "Encrypted": false,
            "Tags": [],
            "DependBundleIDs": []
        },
        {
            "BundleName": "defaultpackage_assets_bundles_audio.bundle",
            "UnityCRC": 0,
            "FileHash": "6f54624a584ed4eda4371aac38ba0f54",
            "FileCRC": 0,
            "FileSize": 1872,
            "Encrypted": false,
            "Tags": [],
            "DependBundleIDs": []
        },
        {
            "BundleName": "defaultpackage_assets_bundles_code.bundle",
            "UnityCRC": 0,
            "FileHash": "b71e51f846aa58d8906e4331a16e2d7a",
            "FileCRC": 0,
            "FileSize": 124928,
            "Encrypted": false,
            "Tags": [],
            "DependBundleIDs": []
        },
        {
            "BundleName": "defaultpackage_assets_bundles_config.bundle",
            "UnityCRC": 0,
            "FileHash": "1650e3240683b6ded4b30297b344cb92",
            "FileCRC": 0,
            "FileSize": 76299,
            "Encrypted": false,
            "Tags": [],
            "DependBundleIDs": []
        },
        {
            "BundleName": "defaultpackage_assets_bundles_font_common.bundle",
            "UnityCRC": 0,
            "FileHash": "76aa21f5159ccdf38020c72b2df0605c",
            "FileCRC": 0,
            "FileSize": 18231296,
            "Encrypted": false,
            "Tags": [],
            "DependBundleIDs": []
        },
        {
            "BundleName": "defaultpackage_assets_bundles_font_textmesh_pro_fonts.bundle",
            "UnityCRC": 0,
            "FileHash": "9a5376c364da990a0c8c17436fe14180",
            "FileCRC": 0,
            "FileSize": 354764,
            "Encrypted": false,
            "Tags": [],
            "DependBundleIDs": []
        },
        {
            "BundleName": "defaultpackage_assets_bundles_font_textmesh_pro_resources.bundle",
            "UnityCRC": 0,
            "FileHash": "b4b4969a498429f127457f21d5ecd2cb",
            "FileCRC": 0,
            "FileSize": 2216,
            "Encrypted": false,
            "Tags": [],
            "DependBundleIDs": []
        },
        {
            "BundleName": "defaultpackage_assets_bundles_font_textmesh_pro_resources_fonts_&_materials.bundle",
            "UnityCRC": 0,
            "FileHash": "4ef6cff6248807019c6b43a6bd4cc3ed",
            "FileCRC": 0,
            "FileSize": 2276415,
            "Encrypted": false,
            "Tags": [],
            "DependBundleIDs": []
        },
        {
            "BundleName": "defaultpackage_assets_bundles_font_textmesh_pro_resources_sprite_assets.bundle",
            "UnityCRC": 0,
            "FileHash": "2ebba489bfaba68ffb6473e7793c7549",
            "FileCRC": 0,
            "FileSize": 13441,
            "Encrypted": false,
            "Tags": [],
            "DependBundleIDs": []
        },
        {
            "BundleName": "defaultpackage_assets_bundles_font_textmesh_pro_resources_style_sheets.bundle",
            "UnityCRC": 0,
            "FileHash": "1b4e7c7090d2c14ec886e33d59ed3b68",
            "FileCRC": 0,
            "FileSize": 5539,
            "Encrypted": false,
            "Tags": [],
            "DependBundleIDs": []
        },
        {
            "BundleName": "defaultpackage_assets_bundles_font_textmesh_pro_sprites.bundle",
            "UnityCRC": 0,
            "FileHash": "5b732f3131dfc2cc17a49089edd30e86",
            "FileCRC": 0,
            "FileSize": 116470,
            "Encrypted": false,
            "Tags": [],
            "DependBundleIDs": []
        },
        {
            "BundleName": "defaultpackage_assets_bundles_hotfixdlls.bundle",
            "UnityCRC": 0,
            "FileHash": "10071be32a5aaa072fa15cfa540c8282",
            "FileCRC": 0,
            "FileSize": 239629,
            "Encrypted": false,
            "Tags": [],
            "DependBundleIDs": []
        },
        {
            "BundleName": "defaultpackage_assets_bundles_image_home.bundle",
            "UnityCRC": 0,
            "FileHash": "55fc4c2530bccd8167ff198dedc83be5",
            "FileCRC": 0,
            "FileSize": 548505,
            "Encrypted": false,
            "Tags": [],
            "DependBundleIDs": []
        },
        {
            "BundleName": "defaultpackage_assets_bundles_image_item.bundle",
            "UnityCRC": 0,
            "FileHash": "1d8647a73d7a9946950b7858480ed159",
            "FileCRC": 0,
            "FileSize": 248654,
            "Encrypted": false,
            "Tags": [],
            "DependBundleIDs": []
        },
        {
            "BundleName": "defaultpackage_assets_bundles_language.bundle",
            "UnityCRC": 0,
            "FileHash": "ea2ac785529b51a5d4c12d6e66d95e2e",
            "FileCRC": 0,
            "FileSize": 10309,
            "Encrypted": false,
            "Tags": [],
            "DependBundleIDs": []
        },
        {
            "BundleName": "defaultpackage_assets_bundles_materials.bundle",
            "UnityCRC": 0,
            "FileHash": "af5b8d46df25549317e35520a613fc5c",
            "FileCRC": 0,
            "FileSize": 65722,
            "Encrypted": false,
            "Tags": [],
            "DependBundleIDs": []
        },
        {
            "BundleName": "defaultpackage_assets_bundles_materials_common.bundle",
            "UnityCRC": 0,
            "FileHash": "bc255f6adc0ef419020c24b2bbfd7630",
            "FileCRC": 0,
            "FileSize": 6961,
            "Encrypted": false,
            "Tags": [],
            "DependBundleIDs": []
        },
        {
            "BundleName": "defaultpackage_assets_bundles_models.bundle",
            "UnityCRC": 0,
            "FileHash": "19548d52947d46dd6221d3a9f7ab6a22",
            "FileCRC": 0,
            "FileSize": 257516,
            "Encrypted": false,
            "Tags": [],
            "DependBundleIDs": []
        },
        {
            "BundleName": "defaultpackage_assets_bundles_prefabs_core.bundle",
            "UnityCRC": 0,
            "FileHash": "f8dc174969bc8ef188ff3239ddbabbba",
            "FileCRC": 0,
            "FileSize": 21540,
            "Encrypted": false,
            "Tags": [],
            "DependBundleIDs": []
        },
        {
            "BundleName": "defaultpackage_assets_bundles_prefabs_entity.bundle",
            "UnityCRC": 0,
            "FileHash": "384c6aae7691cd2b80181a3c3e2bb158",
            "FileCRC": 0,
            "FileSize": 105069,
            "Encrypted": false,
            "Tags": [],
            "DependBundleIDs": []
        },
        {
            "BundleName": "defaultpackage_assets_bundles_prefabs_entity_effect.bundle",
            "UnityCRC": 0,
            "FileHash": "b15a3d5b06438fdd1ae609d31f973acd",
            "FileCRC": 0,
            "FileSize": 615908,
            "Encrypted": false,
            "Tags": [],
            "DependBundleIDs": []
        },
        {
            "BundleName": "defaultpackage_assets_bundles_prefabs_ui.bundle",
            "UnityCRC": 0,
            "FileHash": "a30367653b5d82f1ed53f0f71280c57a",
            "FileCRC": 0,
            "FileSize": 730625,
            "Encrypted": false,
            "Tags": [],
            "DependBundleIDs": []
        },
        {
            "BundleName": "defaultpackage_assets_bundles_prefabs_ui_items.bundle",
            "UnityCRC": 0,
            "FileHash": "540d436328045b4ec7e2086e3662a596",
            "FileCRC": 0,
            "FileSize": 17340,
            "Encrypted": false,
            "Tags": [],
            "DependBundleIDs": []
        },
        {
            "BundleName": "defaultpackage_assets_bundles_scenes.bundle",
            "UnityCRC": 0,
            "FileHash": "a1f19e2b74d250cf6b3230fda5fb1203",
            "FileCRC": 0,
            "FileSize": 17906,
            "Encrypted": false,
            "Tags": [],
            "DependBundleIDs": []
        },
        {
            "BundleName": "defaultpackage_assets_bundles_scriptableassets_core.bundle",
            "UnityCRC": 0,
            "FileHash": "a770d343a07e4ae3d72899a9e0b6822c",
            "FileCRC": 0,
            "FileSize": 914,
            "Encrypted": false,
            "Tags": [],
            "DependBundleIDs": []
        },
        {
            "BundleName": "defaultpackage_assets_bundles_sprites_avatar.bundle",
            "UnityCRC": 0,
            "FileHash": "4321c10b9a72bf04c322768ffb824923",
            "FileCRC": 0,
            "FileSize": 1764732,
            "Encrypted": false,
            "Tags": [],
            "DependBundleIDs": []
        },
        {
            "BundleName": "defaultpackage_assets_bundles_sprites_common.bundle",
            "UnityCRC": 0,
            "FileHash": "9d10b0b17b5ea04de20f88ee3830760b",
            "FileCRC": 0,
            "FileSize": 28187,
            "Encrypted": false,
            "Tags": [],
            "DependBundleIDs": []
        },
        {
            "BundleName": "defaultpackage_assets_bundles_sprites_ui_iconmisc.bundle",
            "UnityCRC": 0,
            "FileHash": "4aac4fb09618abf7345726160dfacad0",
            "FileCRC": 0,
            "FileSize": 52630,
            "Encrypted": false,
            "Tags": [],
            "DependBundleIDs": []
        },
        {
            "BundleName": "defaultpackage_assets_bundles_sprites_ui_toast.bundle",
            "UnityCRC": 0,
            "FileHash": "607b2dd1e71d9e1ba676bccfdd5a2403",
            "FileCRC": 0,
            "FileSize": 3555,
            "Encrypted": false,
            "Tags": [],
            "DependBundleIDs": []
        },
        {
            "BundleName": "defaultpackage_assets_bundles_textures.bundle",
            "UnityCRC": 0,
            "FileHash": "9692b1148a13e9c45822d0afa450d1ae",
            "FileCRC": 0,
            "FileSize": 42394,
            "Encrypted": false,
            "Tags": [],
            "DependBundleIDs": []
        },
        {
            "BundleName": "defaultpackage_assets_bundles_ui_uibag.bundle",
            "UnityCRC": 0,
            "FileHash": "5c457d8879a208e4ce2b51e2289b3607",
            "FileCRC": 0,
            "FileSize": 3637,
            "Encrypted": false,
            "Tags": [],
            "DependBundleIDs": []
        },
        {
            "BundleName": "defaultpackage_assets_bundles_ui_uicommon.bundle",
            "UnityCRC": 0,
            "FileHash": "452488c2b51e0a8f914e4766fab07190",
            "FileCRC": 0,
            "FileSize": 487482,
            "Encrypted": false,
            "Tags": [],
            "DependBundleIDs": []
        },
        {
            "BundleName": "defaultpackage_assets_bundles_ui_uicommonavatar.bundle",
            "UnityCRC": 0,
            "FileHash": "535623d86950166f7b87dea3d6b4e8ba",
            "FileCRC": 0,
            "FileSize": 1827739,
            "Encrypted": false,
            "Tags": [],
            "DependBundleIDs": []
        },
        {
            "BundleName": "defaultpackage_assets_bundles_ui_uiloading.bundle",
            "UnityCRC": 0,
            "FileHash": "43b6be108e6da758e1fc9f662fda8337",
            "FileCRC": 0,
            "FileSize": 454,
            "Encrypted": false,
            "Tags": [],
            "DependBundleIDs": []
        },
        {
            "BundleName": "defaultpackage_assets_bundles_ui_uilogin.bundle",
            "UnityCRC": 0,
            "FileHash": "8845047a89f190271507cde086e81517",
            "FileCRC": 0,
            "FileSize": 1091731,
            "Encrypted": false,
            "Tags": [],
            "DependBundleIDs": []
        },
        {
            "BundleName": "defaultpackage_assets_bundles_ui_uimain.bundle",
            "UnityCRC": 0,
            "FileHash": "2dd6112894c8e14dcc6110dc5251f3f5",
            "FileCRC": 0,
            "FileSize": 967845,
            "Encrypted": false,
            "Tags": [],
            "DependBundleIDs": []
        },
        {
            "BundleName": "defaultpackage_assets_bundles_ui_uiplayer.bundle",
            "UnityCRC": 0,
            "FileHash": "e85b6bc1e6434358822e89059217ce6c",
            "FileCRC": 0,
            "FileSize": 87,
            "Encrypted": false,
            "Tags": [],
            "DependBundleIDs": []
        },
        {
            "BundleName": "defaultpackage_unityshaders.bundle",
            "UnityCRC": 0,
            "FileHash": "10e87469d58b195eb06c36cbcbc162ac",
            "FileCRC": 0,
            "FileSize": 1289759,
            "Encrypted": false,
            "Tags": [],
            "DependBundleIDs": []
        }
    ]
}